spikerplus/__init__.py
spikerplus/net_builder.py
spikerplus/optimizer.py
spikerplus/trainer.py
spikerplus/vhdl_generator.py
spikerplus/dataloaders/__init__.py
spikerplus/dataloaders/audio_mnist_dl.py
spikerplus/dataloaders/mnist_dl.py
spikerplus/dataloaders/shd_dl.py
spikerplus/vhdl/__init__.py
spikerplus/vhdl/add_sub.py
spikerplus/vhdl/addr_converter.py
spikerplus/vhdl/and_mask.py
spikerplus/vhdl/barrier.py
spikerplus/vhdl/barrier_cu.py
spikerplus/vhdl/cmp.py
spikerplus/vhdl/cnt.py
spikerplus/vhdl/decoder.py
spikerplus/vhdl/headers.py
spikerplus/vhdl/layer.py
spikerplus/vhdl/lif_neuron.py
spikerplus/vhdl/lif_neuron_cu.py
spikerplus/vhdl/lif_neuron_dp.py
spikerplus/vhdl/multi_cycle.py
spikerplus/vhdl/multi_cycle_cu.py
spikerplus/vhdl/multi_cycle_dp.py
spikerplus/vhdl/multi_cycle_lif.py
spikerplus/vhdl/multi_input.py
spikerplus/vhdl/multi_input_cu.py
spikerplus/vhdl/multi_input_dp.py
spikerplus/vhdl/multi_input_lif.py
spikerplus/vhdl/multiplier.py
spikerplus/vhdl/mux.py
spikerplus/vhdl/network.py
spikerplus/vhdl/reg.py
spikerplus/vhdl/rom.py
spikerplus/vhdl/shifter.py
spikerplus/vhdl/single_lif_bram.py
spikerplus/vhdl/spiker_pkg.py
spikerplus/vhdl/testbench.py
spikerplus/vhdl/utils.py
spikerplus/vhdl/vhdl.py
spikerplus/vhdl/vhdl_or.py
spikerplus/vhdl/vhdltools/__init__.py
spikerplus/vhdl/vhdltools/architecture.py
spikerplus/vhdl/vhdltools/case_statement.py
spikerplus/vhdl/vhdltools/component.py
spikerplus/vhdl/vhdltools/constant.py
spikerplus/vhdl/vhdltools/custom_types.py
spikerplus/vhdl/vhdltools/dict_code.py
spikerplus/vhdl/vhdltools/entity.py
spikerplus/vhdl/vhdltools/files.py
spikerplus/vhdl/vhdltools/for_statement.py
spikerplus/vhdl/vhdltools/format_text.py
spikerplus/vhdl/vhdltools/generic.py
spikerplus/vhdl/vhdltools/if_statement.py
spikerplus/vhdl/vhdltools/instance.py
spikerplus/vhdl/vhdltools/library_vhdl.py
spikerplus/vhdl/vhdltools/license_text.py
spikerplus/vhdl/vhdltools/list_code.py
spikerplus/vhdl/vhdltools/map_signals.py
spikerplus-2.0.3.dist-info/METADATA
spikerplus-2.0.3.dist-info/WHEEL
spikerplus-2.0.3.dist-info/top_level.txt
spikerplus-2.0.3.dist-info/RECORD
