Metadata-Version: 2.2
Name: spikerplus
Version: 2.0.3
Summary: Build, train, optimize and generate hardware accelerators for Spiking Neural Networks usign VHDL
Home-page: https://github.com/yourusername/your_package
Author: Alessio Carpegna
Author-email: alessio.carpegna@polito.it
Classifier: Programming Language :: Python :: 3
Classifier: License :: OSI Approved :: MIT License
Classifier: Operating System :: OS Independent
Requires-Python: >=3.9
Requires-Dist: numpy
Requires-Dist: torch
Requires-Dist: snntorch
Dynamic: author
Dynamic: author-email
Dynamic: classifier
Dynamic: description
Dynamic: description-content-type
Dynamic: home-page
Dynamic: requires-dist
Dynamic: requires-python
Dynamic: summary
